README.md
src/xwquery_wrapper.py
xwquery-0.0.1.4.dist-info/METADATA
xwquery-0.0.1.4.dist-info/WHEEL
xwquery-0.0.1.4.dist-info/licenses/LICENSE
xwquery-0.0.1.4.dist-info/RECORD
