Metadata-Version: 2.4
Name: xwquery
Version: 0.0.1.4
Summary: Convenience wrapper for exonware-xwquery - provides 'import xwquery' alias
Project-URL: Homepage, https://exonware.com
Project-URL: Repository, https://github.com/exonware/xwquery
Project-URL: Documentation, https://github.com/exonware/xwquery#readme
Author-email: "Eng. Muhammad AlShehri" <connect@exonware.com>
License: MIT
License-File: LICENSE
Keywords: conversion,cypher,data,exonware,graphql,query,sparql,sql
Classifier: Development Status :: 3 - Alpha
Classifier: Intended Audience :: Developers
Classifier: License :: OSI Approved :: MIT License
Classifier: Operating System :: OS Independent
Classifier: Programming Language :: Python :: 3
Classifier: Programming Language :: Python :: 3.8
Classifier: Programming Language :: Python :: 3.9
Classifier: Programming Language :: Python :: 3.10
Classifier: Programming Language :: Python :: 3.11
Classifier: Programming Language :: Python :: 3.12
Classifier: Topic :: Database :: Database Engines/Servers
Classifier: Topic :: Software Development :: Libraries :: Python Modules
Requires-Python: >=3.8
Requires-Dist: exonware-xwquery
Provides-Extra: dev
Requires-Dist: exonware-xwquery[dev]; extra == 'dev'
Provides-Extra: full
Requires-Dist: exonware-xwquery[full]; extra == 'full'
Provides-Extra: lazy
Requires-Dist: exonware-xwquery[lazy]; extra == 'lazy'
